retuve_yolo_plugin/__init__.py
retuve_yolo_plugin/ultrasound.py
retuve_yolo_plugin/utils.py
retuve_yolo_plugin/xray.py
retuve_yolo_plugin/xray_pose.py
retuve_yolo_plugin/xray_utils.py
retuve_yolo_plugin/tools/export.py
retuve_yolo_plugin/training_params/ultrasound.yml
retuve_yolo_plugin/training_params/xray_pose.yml
retuve_yolo_plugin/training_params/xray_seg.yml
retuve_yolo_plugin/weights/v1.0/hip-yolo-us.onnx
retuve_yolo_plugin/weights/v1.0/hip-yolo-us.pt
retuve_yolo_plugin/weights/v1.0/hip-yolo-xray-pose.pt
retuve_yolo_plugin/weights/v1.0/hip-yolo-xray-seg.pt
retuve_yolo_plugin-1.0.0.dist-info/METADATA
retuve_yolo_plugin-1.0.0.dist-info/WHEEL
retuve_yolo_plugin-1.0.0.dist-info/licenses/LICENSE
retuve_yolo_plugin-1.0.0.dist-info/licenses/LICENSE2
retuve_yolo_plugin-1.0.0.dist-info/RECORD
