Metadata-Version: 2.4
Name: retuve-yolo-plugin
Version: 1.0.0
Summary: YOLO AI Plugin for Retuve hip dysplasia analysis
Project-URL: Homepage, https://github.com/radoss-org/retuve-yolo-plugin
Project-URL: Repository, https://github.com/radoss-org/retuve-yolo-plugin
Project-URL: Documentation, https://github.com/radoss-org/retuve
Project-URL: Bug Tracker, https://github.com/radoss-org/retuve-yolo-plugin/issues
Author-email: Sharpz7 <adam.mcarthur62@gmail.com>
License: AGPL-3.0 AND CC-BY-NC-SA-3.0
License-File: LICENSE
License-File: LICENSE2
Keywords: ai,dysplasia,hip,medical,segmentation,yolo
Classifier: Development Status :: 4 - Beta
Classifier: Intended Audience :: Healthcare Industry
Classifier: Intended Audience :: Science/Research
Classifier: License :: OSI Approved :: GNU Affero General Public License v3
Classifier: Operating System :: OS Independent
Classifier: Programming Language :: Python :: 3
Classifier: Programming Language :: Python :: 3.10
Classifier: Programming Language :: Python :: 3.11
Classifier: Programming Language :: Python :: 3.12
Classifier: Topic :: Scientific/Engineering :: Artificial Intelligence
Classifier: Topic :: Scientific/Engineering :: Medical Science Apps.
Requires-Python: <3.13,>=3.10
Requires-Dist: kaleido>=1.0.0
Requires-Dist: retuve>=1.0.0
Requires-Dist: ultralytics>=8.2.48
Provides-Extra: dev
Requires-Dist: black>=25.1.0; extra == 'dev'
Requires-Dist: pytest-xdist>=3.6.1; extra == 'dev'
Requires-Dist: pytest>=7.0.0; extra == 'dev'
